{
  "days": [
    {
      "day": "Monday",
      "seed": "Pumpkin seeds",
      "meals": {
        "morning": "Warm lemon water + 5 soaked almonds + 2 walnuts + 1 tsp chia seeds",

        "breakfast": {
          "name": "Moong Dal Chilla + Paneer",
          "ingredients": {
            "Moong dal (cup)": 0.5,
            "Paneer (g)": 75,
            "Oil (tsp)": 1,
            "Salt": "to taste",
            "Green chilli": 1
          },
          "steps": [
            "Soak moong dal in water for 8 hours or overnight",
            "Drain and grind into smooth batter with little water",
            "Add salt and chopped green chilli",
            "Heat non-stick pan and lightly grease with oil",
            "Pour batter and spread like dosa",
            "Cook both sides until golden",
            "Add grated paneer as stuffing and fold",
            "Serve hot"
          ],
          "prep": [
            "Soak moong dal overnight"
          ]
        },

        "lunch": {
          "name": "Dal + Roti + Salad",
          "ingredients": {
            "Toor/Moong dal (cup)": 0.5,
            "Roti": 2,
            "Oil (tsp)": 1,
            "Jeera": "1 tsp",
            "Garlic cloves": 3
          },
          "steps": [
            "Wash dal and pressure cook with water and salt (3 whistles)",
            "Heat 1 tsp oil in pan, add jeera and garlic",
            "Add cooked dal and simmer for 5–7 minutes",
            "Prepare fresh salad (cucumber, carrot, onion)",
            "Serve with roti"
          ]
        },

        "snack": {
          "name": "Roasted Chana + Pumpkin Seeds",
          "ingredients": {
            "Roasted chana (g)": 30,
            "Pumpkin seeds (tbsp)": 1
          },
          "steps": [
            "Mix roasted chana and pumpkin seeds",
            "Consume as evening snack"
          ]
        },

        "dinner": {
          "name": "Paneer Bhurji (Low Oil)",
          "ingredients": {
            "Paneer (g)": 100,
            "Onion": 1,
            "Tomato": 1,
            "Oil (tsp)": 1
          },
          "steps": [
            "Heat 1 tsp oil in pan",
            "Add chopped onion and sauté till soft",
            "Add tomato and cook until mushy",
            "Add spices (turmeric, salt)",
            "Add crumbled paneer and cook for 2–3 minutes",
            "Serve hot"
          ]
        }
      }
    },

    {
      "day": "Tuesday",
      "seed": "Flax seeds",
      "meals": {
        "morning": "Jeera water + soaked almonds + chia seeds",

        "breakfast": {
          "name": "Vegetable Oats",
          "ingredients": {
            "Oats (cup)": 0.5,
            "Mixed vegetables (cup)": 1,
            "Oil (tsp)": 1
          },
          "steps": [
            "Dry roast oats for 2–3 minutes",
            "Heat oil, add vegetables and sauté",
            "Add oats and water",
            "Cook until soft and thick",
            "Add salt and serve"
          ]
        },

        "lunch": {
          "name": "Rajma + Rice",
          "ingredients": {
            "Rajma (cup)": 0.5,
            "Rice (cup)": 1,
            "Onion": 1,
            "Tomato": 2,
            "Oil (tsp)": 1
          },
          "steps": [
            "Soak rajma overnight",
            "Pressure cook rajma (5–6 whistles)",
            "Heat oil, sauté onion till golden",
            "Add tomato and cook till soft",
            "Add spices and cooked rajma",
            "Simmer for 10 minutes",
            "Cook rice separately and serve"
          ],
          "prep": [
            "Soak rajma overnight"
          ]
        },

        "snack": {
          "name": "Paneer + Flax Seeds",
          "ingredients": {
            "Paneer (g)": 75,
            "Flax seeds (tsp)": 1
          },
          "steps": [
            "Lightly roast flax seeds",
            "Consume with paneer"
          ]
        },

        "dinner": {
          "name": "Tofu Stir Fry",
          "ingredients": {
            "Tofu (g)": 100,
            "Vegetables (cup)": 1,
            "Oil (tsp)": 1
          },
          "steps": [
            "Heat oil in pan",
            "Add vegetables and sauté",
            "Add tofu cubes",
            "Cook on high flame for 5 minutes",
            "Add salt and pepper"
          ]
        }
      }
    },

    {
      "day": "Wednesday",
      "seed": "Sunflower seeds",
      "meals": {
        "morning": "Warm water + soaked nuts + chia seeds",

        "breakfast": {
          "name": "Sprouts Bowl (Curd Optional)",
          "ingredients": {
            "Sprouts (cup)": 1,
            "Curd (optional)": 0.5
          },
          "steps": [
            "Wash sprouts properly",
            "Mix with salt, lemon juice",
            "Add curd if preferred",
            "Alternative: replace curd with lemon only"
          ]
        },

        "lunch": {
          "name": "Chole + Roti",
          "ingredients": {
            "Chole (cup)": 0.5,
            "Roti": 2,
            "Onion": 1,
            "Tomato": 2,
            "Oil (tsp)": 1
          },
          "steps": [
            "Soak chole overnight",
            "Pressure cook chole (5–6 whistles)",
            "Heat oil and sauté onion till golden",
            "Add tomato and cook till soft",
            "Add spices and cooked chole",
            "Simmer for 10 minutes",
            "Serve with roti"
          ],
          "prep": [
            "Soak chole overnight"
          ]
        },

        "snack": {
          "name": "Corn + Peanuts + Sunflower Seeds",
          "ingredients": {
            "Boiled corn (cup)": 1,
            "Peanuts (tbsp)": 1,
            "Sunflower seeds (tbsp)": 1
          },
          "steps": [
            "Mix all ingredients",
            "Add salt and lemon",
            "Serve fresh"
          ]
        },

        "dinner": {
          "name": "Moong Dal Soup",
          "ingredients": {
            "Moong dal (cup)": 0.5,
            "Garlic cloves": 2
          },
          "steps": [
            "Pressure cook dal",
            "Blend lightly",
            "Add garlic tadka",
            "Simmer for 5 minutes",
            "Serve warm"
          ]
        }
      }
    },

    {
      "day": "Thursday",
      "seed": "Pumpkin seeds",
      "meals": {
        "morning": "Jeera water + nuts + chia seeds",

        "breakfast": {
          "name": "Besan Chilla",
          "ingredients": {
            "Besan (cup)": 0.5,
            "Vegetables (cup)": 0.5,
            "Oil (tsp)": 1
          },
          "steps": [
            "Prepare batter with besan and water",
            "Add chopped vegetables",
            "Cook on pan with minimal oil",
            "Flip and cook both sides"
          ]
        },

        "lunch": {
          "name": "Paneer Curry + Roti",
          "ingredients": {
            "Paneer (g)": 100,
            "Onion": 1,
            "Tomato": 2,
            "Oil (tsp)": 1
          },
          "steps": [
            "Cook onion tomato gravy",
            "Add spices",
            "Add paneer cubes",
            "Simmer for 5 minutes"
          ]
        },

        "snack": {
          "name": "Sprouts + Pumpkin Seeds",
          "ingredients": {
            "Sprouts (cup)": 1,
            "Pumpkin seeds (tbsp)": 1
          },
          "steps": [
            "Mix sprouts and seeds",
            "Add lemon and salt"
          ]
        },

        "dinner": {
          "name": "Vegetable Khichdi",
          "ingredients": {
            "Rice (cup)": 0.25,
            "Dal (cup)": 0.25,
            "Vegetables (cup)": 1
          },
          "steps": [
            "Wash rice and dal",
            "Add vegetables and water",
            "Pressure cook (3 whistles)",
            "Serve warm"
          ]
        }
      }
    },

    {
      "day": "Friday",
      "seed": "Flax seeds",
      "meals": {
        "morning": "Warm water + nuts + chia",

        "breakfast": {
          "name": "Upma + Peanuts",
          "ingredients": {
            "Suji (cup)": 0.5,
            "Peanuts (tbsp)": 1,
            "Vegetables (cup)": 1
          },
          "steps": [
            "Dry roast suji",
            "Cook vegetables",
            "Add water and suji",
            "Cook until thick"
          ]
        },

        "lunch": {
          "name": "Tofu Curry + Rice",
          "ingredients": {
            "Tofu (g)": 100,
            "Rice (cup)": 1
          },
          "steps": [
            "Cook tofu in tomato gravy",
            "Cook rice separately",
            "Serve hot"
          ]
        },

        "snack": {
          "name": "Roasted Makhana",
          "ingredients": {
            "Makhana (cup)": 1
          },
          "steps": [
            "Dry roast makhana for 5–7 minutes"
          ]
        },

        "dinner": {
          "name": "Dal + Sabzi + Roti",
          "ingredients": {
            "Dal (cup)": 0.5,
            "Roti": 2
          },
          "steps": [
            "Cook dal",
            "Prepare simple vegetable sabzi",
            "Serve with roti"
          ]
        }
      }
    },

    {
      "day": "Saturday",
      "seed": "Watermelon seeds",
      "meals": {
        "morning": "Lemon water + nuts + chia",

        "breakfast": {
          "name": "Oats + Milk + Seeds + Fruit",
          "ingredients": {
            "Oats (cup)": 0.5,
            "Milk (cup)": 1,
            "Fruit": 1
          },
          "steps": [
            "Cook oats with milk",
            "Add chopped fruit",
            "Add seeds and serve"
          ]
        },

        "lunch": {
          "name": "Rajma + Roti",
          "ingredients": {
            "Rajma (cup)": 0.5,
            "Roti": 2
          },
          "steps": [
            "Cook rajma and serve with roti"
          ]
        },

        "snack": {
          "name": "Paneer + Seeds",
          "ingredients": {
            "Paneer (g)": 75,
            "Seeds (tbsp)": 1
          },
          "steps": [
            "Mix and consume"
          ]
        },

        "dinner": {
          "name": "Tofu Stir Fry",
          "ingredients": {
            "Tofu (g)": 100
          },
          "steps": [
            "Stir fry tofu and vegetables"
          ]
        }
      }
    },

    {
      "day": "Sunday",
      "seed": "Mixed seeds",
      "meals": {
        "morning": "Warm water + nuts + chia",

        "breakfast": {
          "name": "Sprouts + Fruit",
          "ingredients": {
            "Sprouts (cup)": 1,
            "Fruit": 1
          },
          "steps": [
            "Mix sprouts with chopped fruit",
            "Add lemon and salt"
          ]
        },

        "lunch": {
          "name": "Chole + Rice",
          "ingredients": {
            "Chole (cup)": 0.5,
            "Rice (cup)": 1
          },
          "steps": [
            "Soak chole overnight",
            "Pressure cook chole",
            "Prepare onion tomato gravy",
            "Mix and simmer",
            "Serve with rice"
          ],
          "prep": [
            "Soak chole overnight"
          ]
        },

        "snack": {
          "name": "Chana + Seeds",
          "ingredients": {
            "Chana (g)": 30,
            "Seeds (tbsp)": 1
          },
          "steps": [
            "Mix and eat"
          ]
        },

        "dinner": {
          "name": "Light Dal + Salad",
          "ingredients": {
            "Dal (cup)": 0.5
          },
          "steps": [
            "Cook dal",
            "Serve with fresh salad"
          ]
        }
      }
    }
  ]
}
